MAB_algorithm/MAB.py
MAB_algorithm/MABMultiplayer.py
MAB_algorithm/MAB_MC.py
MAB_algorithm/MAButils.py
MAB_algorithm/__init__.py
MAB_algorithm/arm.py
MAB_algorithm/distns.py
MAB_algorithm/mabCutils.cpython-310-x86_64-linux-gnu.so
MAB_algorithm/mabCutils.cpython-39-x86_64-linux-gnu.so
MAB_algorithm/mabCutils.pyi
MAB_algorithm/mabplot.py
MAB_algorithm-0.0.2.dist-info/LICENSE
MAB_algorithm-0.0.2.dist-info/METADATA
MAB_algorithm-0.0.2.dist-info/WHEEL
MAB_algorithm-0.0.2.dist-info/top_level.txt
MAB_algorithm-0.0.2.dist-info/RECORD
