Metadata-Version: 2.1
Name: MAB-algorithm
Version: 0.0.2
Summary: A modern multi-armed bandits library.
Home-page: https://github.com/Antares0982/MAB-algorithm-template
Author: Antares
Author-email: Antares0982@gmail.com
License: MIT
Platform: Windows
Platform: Linux
License-File: LICENSE
Requires-Dist: scipy
Requires-Dist: numpy
Requires-Dist: pandas
Requires-Dist: matplotlib
